simplesqlserver/__init__.py
simple_sql_server-0.0.2.dist-info/LICENSE
simple_sql_server-0.0.2.dist-info/METADATA
simple_sql_server-0.0.2.dist-info/WHEEL
simple_sql_server-0.0.2.dist-info/top_level.txt
simple_sql_server-0.0.2.dist-info/RECORD
