Metadata-Version: 2.1
Name: simple-sql-server
Version: 0.0.2
Summary: Python package to perform basic SQL Server functions
Home-page: https://github.com/lsimon14/simple-sql-server
Author: Luke Simon
License: UNKNOWN
Platform: UNKNOWN
Classifier: Programming Language :: Python :: 3
Classifier: Operating System :: OS Independent
Requires-Python: >=3
Requires-Dist: bcpy
Requires-Dist: pyodbc
